python_starter_pack/__init__.py
python_starter_pack/funcs.py
python_starter_pack-0.2.0.dist-info/LICENSE
python_starter_pack-0.2.0.dist-info/METADATA
python_starter_pack-0.2.0.dist-info/WHEEL
python_starter_pack-0.2.0.dist-info/entry_points.txt
python_starter_pack-0.2.0.dist-info/top_level.txt
python_starter_pack-0.2.0.dist-info/RECORD
