Metadata-Version: 2.1
Name: python-starter-pack
Version: 0.2.0
Summary: A starter pack for Python modules.
Home-page: https://github.com/apiad/python-starter-pack
Author: Alejandro Piad
Author-email: apiad@apiad.net
License: MIT
Download-URL: https://github.com/apiad/python-starter-pack/tarball/0.2.0
Platform: UNKNOWN
Classifier: Development Status :: 4 - Beta
Classifier: License :: OSI Approved :: MIT License
Classifier: Programming Language :: Python :: 3.6
Classifier: Topic :: Software Development :: Libraries :: Python Modules
Requires-Dist: toml
